{
  "resolvedId": "/home/yalnguembu/Perso/quonte/components/form/TextInput.vue",
  "transforms": [
    {
      "name": "vite:load-fallback",
      "result": "<template>\n  <div class=\"w-full\">\n    <label class=\"font-500 dark:text-gray-100\"> {{ props.label }} </label>\n    <input\n      :class=\"[\n        'rounded border px-3 py-1 w-full mt-2 bg-transparent outline-none dark:text-gray-100 dark:border-gray-700',\n        errors.length\n          ? 'outline-red-500'\n          : isValid\n          ? 'outline-green-500 dark:outline-green-600'\n          : 'focus:outline-blue-500 dark:focus:outline-blue-600',\n      ]\"\n      type=\"text\"\n      :placeholder=\"props.placeholder\"\n      :value=\"props.modelValue\"\n      @input=\"(event :Event)=>emit('update:modelValue', (event.target as HTMLInputElement).value)\"\n    />\n    <p\n      :data-test=\"error.$property\"\n      v-show=\"props.errors?.length\"\n      v-for=\"error in props.errors\"\n      :key=\"error.$uid\"\n      class=\"pt-1 text-red-500 transition delay-500 text-sm\"\n    >\n      {{ error.$message }}\n    </p>\n  </div>\n</template>\n<script setup lang=\"ts\">\nimport type { ErrorObject } from \"@vuelidate/core\";\n\nconst emit = defineEmits([\"update:modelValue\"]);\nconst props = withDefaults(\n  defineProps<{\n    modelValue: string;\n    label?: string;\n    placeholder?: string;\n    errors?: ErrorObject[];\n    isValid?: boolean;\n  }>(),\n  {\n    isValid: false,\n    errors: () => [],\n  }\n);\n</script>\n",
      "start": 1713208779304,
      "end": 1713208779926,
      "sourcemaps": null
    },
    {
      "name": "nuxt:layer-aliasing",
      "start": 1713208779926,
      "end": 1713208779926,
      "order": "pre"
    },
    {
      "name": "nuxt:layer-aliasing",
      "start": 1713208779926,
      "end": 1713208779926,
      "order": "pre"
    },
    {
      "name": "nuxt:server-devonly:transform",
      "start": 1713208779926,
      "end": 1713208779926,
      "order": "pre"
    },
    {
      "name": "nuxt:server-devonly:transform",
      "start": 1713208779926,
      "end": 1713208779926,
      "order": "pre"
    },
    {
      "name": "unplugin-vue-i18n",
      "start": 1713208779926,
      "end": 1713208779926,
      "order": "pre"
    },
    {
      "name": "unplugin-vue-i18n",
      "start": 1713208779926,
      "end": 1713208779926,
      "order": "pre"
    },
    {
      "name": "nuxtjs:i18n-macros-transform",
      "start": 1713208779926,
      "end": 1713208779926,
      "order": "pre"
    },
    {
      "name": "nuxtjs:i18n-macros-transform",
      "start": 1713208779926,
      "end": 1713208779926,
      "order": "pre"
    },
    {
      "name": "nuxt:client-fallback-auto-id",
      "start": 1713208779926,
      "end": 1713208779926,
      "order": "pre"
    },
    {
      "name": "server-only-component-transform",
      "start": 1713208779926,
      "end": 1713208779926,
      "order": "pre"
    },
    {
      "name": "vite:css",
      "start": 1713208779926,
      "end": 1713208779926,
      "order": "normal"
    },
    {
      "name": "vite:esbuild",
      "start": 1713208779926,
      "end": 1713208779926,
      "order": "normal"
    },
    {
      "name": "vite:json",
      "start": 1713208779926,
      "end": 1713208779926,
      "order": "normal"
    },
    {
      "name": "vite:worker",
      "start": 1713208779926,
      "end": 1713208779926,
      "order": "normal"
    },
    {
      "name": "vite:vue",
      "result": "import _sfc_main from \"/home/yalnguembu/Perso/quonte/components/form/TextInput.vue?vue&type=script&setup=true&lang.ts\";\nexport * from \"/home/yalnguembu/Perso/quonte/components/form/TextInput.vue?vue&type=script&setup=true&lang.ts\";\nimport { useSSRContext as __vite_useSSRContext } from \"vue\";\nconst _sfc_setup = _sfc_main.setup;\n_sfc_main.setup = (props, ctx) => {\n  const ssrContext = __vite_useSSRContext();\n  (ssrContext.modules || (ssrContext.modules = /* @__PURE__ */ new Set())).add(\"components/form/TextInput.vue\");\n  return _sfc_setup ? _sfc_setup(props, ctx) : void 0;\n};\nexport default _sfc_main;\n",
      "start": 1713208779926,
      "end": 1713208779982,
      "order": "normal",
      "sourcemaps": {
        "mappings": ""
      }
    },
    {
      "name": "vite:vue-jsx",
      "start": 1713208779982,
      "end": 1713208779982,
      "order": "normal"
    },
    {
      "name": "replace",
      "start": 1713208779982,
      "end": 1713208779982,
      "order": "normal"
    },
    {
      "name": "replace",
      "start": 1713208779982,
      "end": 1713208779982,
      "order": "normal"
    },
    {
      "name": "nuxt:remove-plugin-metadata",
      "start": 1713208779983,
      "end": 1713208779983,
      "order": "normal"
    },
    {
      "name": "nuxt:remove-plugin-metadata",
      "start": 1713208779983,
      "end": 1713208779983,
      "order": "normal"
    },
    {
      "name": "nuxt:components:imports",
      "start": 1713208779983,
      "end": 1713208779983,
      "order": "normal"
    },
    {
      "name": "replace",
      "start": 1713208779983,
      "end": 1713208779983,
      "order": "normal"
    },
    {
      "name": "ssr-styles",
      "start": 1713208779983,
      "end": 1713208779983,
      "order": "normal"
    },
    {
      "name": "vite:define",
      "start": 1713208779984,
      "end": 1713208779984,
      "order": "normal"
    },
    {
      "name": "vite:css-post",
      "start": 1713208779984,
      "end": 1713208779984,
      "order": "normal"
    },
    {
      "name": "vite:build-html",
      "start": 1713208779984,
      "end": 1713208779984,
      "order": "normal"
    },
    {
      "name": "vite:worker-import-meta-url",
      "start": 1713208779985,
      "end": 1713208779985,
      "order": "normal"
    },
    {
      "name": "vite:asset-import-meta-url",
      "start": 1713208779985,
      "end": 1713208779985,
      "order": "normal"
    },
    {
      "name": "commonjs",
      "start": 1713208779985,
      "end": 1713208779985,
      "order": "normal"
    },
    {
      "name": "vite:dynamic-import-vars",
      "start": 1713208779985,
      "end": 1713208779985,
      "order": "normal"
    },
    {
      "name": "vite:import-glob",
      "start": 1713208779985,
      "end": 1713208779985,
      "order": "normal"
    },
    {
      "name": "nuxt:composable-keys",
      "start": 1713208779985,
      "end": 1713208779985,
      "order": "post"
    },
    {
      "name": "nuxt:composable-keys",
      "start": 1713208779985,
      "end": 1713208779985,
      "order": "post"
    },
    {
      "name": "unhead:remove-server-composables",
      "start": 1713208779985,
      "end": 1713208779985,
      "order": "post"
    },
    {
      "name": "unhead:use-seo-meta-transform",
      "start": 1713208779986,
      "end": 1713208779986,
      "order": "post"
    },
    {
      "name": "unhead:use-seo-meta-transform",
      "start": 1713208779986,
      "end": 1713208779986,
      "order": "post"
    },
    {
      "name": "nuxtjs:i18n-resource",
      "start": 1713208779986,
      "end": 1713208779986,
      "order": "post"
    },
    {
      "name": "nuxtjs:i18n-resource",
      "start": 1713208779986,
      "end": 1713208779986,
      "order": "post"
    },
    {
      "name": "nuxtjs:i18n-meta-deprecation",
      "start": 1713208779986,
      "end": 1713208779986,
      "order": "post"
    },
    {
      "name": "nuxtjs:i18n-meta-deprecation",
      "start": 1713208779986,
      "end": 1713208779986,
      "order": "post"
    },
    {
      "name": "nuxt:imports-transform",
      "start": 1713208779986,
      "end": 1713208779988,
      "order": "post"
    },
    {
      "name": "nuxt:imports-transform",
      "start": 1713208779986,
      "end": 1713208779988,
      "order": "post"
    },
    {
      "name": "unctx:transform",
      "start": 1713208779988,
      "end": 1713208779988,
      "order": "post"
    },
    {
      "name": "unctx:transform",
      "start": 1713208779988,
      "end": 1713208779988,
      "order": "post"
    },
    {
      "name": "nuxt:pages-macros-transform",
      "start": 1713208779989,
      "end": 1713208779989,
      "order": "post"
    },
    {
      "name": "nuxt:pages-macros-transform",
      "start": 1713208779989,
      "end": 1713208779990,
      "order": "post"
    },
    {
      "name": "nuxt:tree-shake-template",
      "start": 1713208779991,
      "end": 1713208779991,
      "order": "post"
    },
    {
      "name": "nuxt:components-loader",
      "start": 1713208779992,
      "end": 1713208779992,
      "order": "post"
    },
    {
      "name": "nuxt:tree-shake-composables:transform",
      "start": 1713208779992,
      "end": 1713208779992,
      "order": "post"
    },
    {
      "name": "vite:build-import-analysis",
      "start": 1713208779992,
      "end": 1713208779992,
      "order": "normal"
    },
    {
      "name": "vite:reporter",
      "start": 1713208779992,
      "end": 1713208779993,
      "order": "normal"
    }
  ]
}
