{
  "resolvedId": "/home/yalnguembu/Perso/quonte/components/LinkWrapper.vue?vue&type=script&setup=true&lang.ts",
  "transforms": [
    {
      "name": "vite:vue",
      "result": "import { defineComponent as _defineComponent } from 'vue'\nimport { renderSlot as _renderSlot, openBlock as _openBlock, createElementBlock as _createElementBlock, createCommentVNode as _createCommentVNode, resolveComponent as _resolveComponent, normalizeClass as _normalizeClass, withCtx as _withCtx, createBlock as _createBlock } from \"vue\"\n\nconst _hoisted_1 = [\"href\", \"title\"]\n\n\nexport default /*#__PURE__*/_defineComponent({\n  __name: 'LinkWrapper',\n  props: {\n  title: {\n    type: String,\n  },\n  path: {\n    type: String,\n    required: true,\n  },\n  isExternal: {\n    type: Boolean,\n    default: false,\n  },\n},\n  setup(__props) {\n\n\n\nreturn (_ctx: any,_cache: any) => {\n  const _component_RouterLink = _resolveComponent(\"RouterLink\")!\n\n  return (__props.isExternal)\n    ? (_openBlock(), _createElementBlock(\"a\", {\n        key: 0,\n        href: __props.path,\n        title: __props.title,\n        target: \"_blank\",\n        rel: \"noopener noreferrer\"\n      }, [\n        _renderSlot(_ctx.$slots, \"default\")\n      ], 8, _hoisted_1))\n    : (_openBlock(), _createBlock(_component_RouterLink, {\n        key: 1,\n        to: __props.path,\n        title: __props.title,\n        class: _normalizeClass(_ctx.theme)\n      }, {\n        default: _withCtx(() => [\n          _renderSlot(_ctx.$slots, \"default\")\n        ]),\n        _: 3\n      }, 8, [\"to\", \"title\", \"class\"]))\n}\n}\n\n})",
      "start": 1713208772443,
      "end": 1713208772444
    },
    {
      "name": "nuxt:layer-aliasing",
      "start": 1713208772444,
      "end": 1713208772444,
      "order": "pre"
    },
    {
      "name": "nuxt:server-devonly:transform",
      "start": 1713208772444,
      "end": 1713208772444,
      "order": "pre"
    },
    {
      "name": "unplugin-vue-i18n",
      "start": 1713208772444,
      "end": 1713208772444,
      "order": "pre"
    },
    {
      "name": "nuxtjs:i18n-macros-transform",
      "start": 1713208772444,
      "end": 1713208772444,
      "order": "pre"
    },
    {
      "name": "nuxt:client-fallback-auto-id",
      "start": 1713208772444,
      "end": 1713208772444,
      "order": "pre"
    },
    {
      "name": "vite:css",
      "start": 1713208772444,
      "end": 1713208772444,
      "order": "normal"
    },
    {
      "name": "vite:esbuild",
      "result": "import { defineComponent as _defineComponent } from \"vue\";\nimport { renderSlot as _renderSlot, openBlock as _openBlock, createElementBlock as _createElementBlock, resolveComponent as _resolveComponent, normalizeClass as _normalizeClass, withCtx as _withCtx, createBlock as _createBlock } from \"vue\";\nconst _hoisted_1 = [\"href\", \"title\"];\nexport default /* @__PURE__ */ _defineComponent({\n  __name: \"LinkWrapper\",\n  props: {\n    title: {\n      type: String\n    },\n    path: {\n      type: String,\n      required: true\n    },\n    isExternal: {\n      type: Boolean,\n      default: false\n    }\n  },\n  setup(__props) {\n    return (_ctx, _cache) => {\n      const _component_RouterLink = _resolveComponent(\"RouterLink\");\n      return __props.isExternal ? (_openBlock(), _createElementBlock(\"a\", {\n        key: 0,\n        href: __props.path,\n        title: __props.title,\n        target: \"_blank\",\n        rel: \"noopener noreferrer\"\n      }, [\n        _renderSlot(_ctx.$slots, \"default\")\n      ], 8, _hoisted_1)) : (_openBlock(), _createBlock(_component_RouterLink, {\n        key: 1,\n        to: __props.path,\n        title: __props.title,\n        class: _normalizeClass(_ctx.theme)\n      }, {\n        default: _withCtx(() => [\n          _renderSlot(_ctx.$slots, \"default\")\n        ]),\n        _: 3\n      }, 8, [\"to\", \"title\", \"class\"]));\n    };\n  }\n});\n",
      "start": 1713208772444,
      "end": 1713208772463,
      "order": "normal",
      "sourcemaps": {
        "version": 3,
        "sources": [
          "/home/yalnguembu/Perso/quonte/components/LinkWrapper.vue?vue&type=script&setup=true&lang.ts"
        ],
        "sourcesContent": [
          "import { defineComponent as _defineComponent } from 'vue'\nimport { renderSlot as _renderSlot, openBlock as _openBlock, createElementBlock as _createElementBlock, createCommentVNode as _createCommentVNode, resolveComponent as _resolveComponent, normalizeClass as _normalizeClass, withCtx as _withCtx, createBlock as _createBlock } from \"vue\"\n\nconst _hoisted_1 = [\"href\", \"title\"]\n\n\nexport default /*#__PURE__*/_defineComponent({\n  __name: 'LinkWrapper',\n  props: {\n  title: {\n    type: String,\n  },\n  path: {\n    type: String,\n    required: true,\n  },\n  isExternal: {\n    type: Boolean,\n    default: false,\n  },\n},\n  setup(__props) {\n\n\n\nreturn (_ctx: any,_cache: any) => {\n  const _component_RouterLink = _resolveComponent(\"RouterLink\")!\n\n  return (__props.isExternal)\n    ? (_openBlock(), _createElementBlock(\"a\", {\n        key: 0,\n        href: __props.path,\n        title: __props.title,\n        target: \"_blank\",\n        rel: \"noopener noreferrer\"\n      }, [\n        _renderSlot(_ctx.$slots, \"default\")\n      ], 8, _hoisted_1))\n    : (_openBlock(), _createBlock(_component_RouterLink, {\n        key: 1,\n        to: __props.path,\n        title: __props.title,\n        class: _normalizeClass(_ctx.theme)\n      }, {\n        default: _withCtx(() => [\n          _renderSlot(_ctx.$slots, \"default\")\n        ]),\n        _: 3\n      }, 8, [\"to\", \"title\", \"class\"]))\n}\n}\n\n})"
        ],
        "mappings": "AAAA,SAAS,mBAAmB,wBAAwB;AACpD,SAAS,cAAc,aAAa,aAAa,YAAY,sBAAsB,qBAAgE,oBAAoB,mBAAmB,kBAAkB,iBAAiB,WAAW,UAAU,eAAe,oBAAoB;AAErR,MAAM,aAAa,CAAC,QAAQ,OAAO;AAGnC,eAA4B,iCAAiB;AAAA,EAC3C,QAAQ;AAAA,EACR,OAAO;AAAA,IACP,OAAO;AAAA,MACL,MAAM;AAAA,IACR;AAAA,IACA,MAAM;AAAA,MACJ,MAAM;AAAA,MACN,UAAU;AAAA,IACZ;AAAA,IACA,YAAY;AAAA,MACV,MAAM;AAAA,MACN,SAAS;AAAA,IACX;AAAA,EACF;AAAA,EACE,MAAM,SAAS;AAIjB,WAAO,CAAC,MAAU,WAAgB;AAChC,YAAM,wBAAwB,kBAAkB,YAAY;AAE5D,aAAQ,QAAQ,cACX,WAAW,GAAG,oBAAoB,KAAK;AAAA,QACtC,KAAK;AAAA,QACL,MAAM,QAAQ;AAAA,QACd,OAAO,QAAQ;AAAA,QACf,QAAQ;AAAA,QACR,KAAK;AAAA,MACP,GAAG;AAAA,QACD,YAAY,KAAK,QAAQ,SAAS;AAAA,MACpC,GAAG,GAAG,UAAU,MACf,WAAW,GAAG,aAAa,uBAAuB;AAAA,QACjD,KAAK;AAAA,QACL,IAAI,QAAQ;AAAA,QACZ,OAAO,QAAQ;AAAA,QACf,OAAO,gBAAgB,KAAK,KAAK;AAAA,MACnC,GAAG;AAAA,QACD,SAAS,SAAS,MAAM;AAAA,UACtB,YAAY,KAAK,QAAQ,SAAS;AAAA,QACpC,CAAC;AAAA,QACD,GAAG;AAAA,MACL,GAAG,GAAG,CAAC,MAAM,SAAS,OAAO,CAAC;AAAA,IACpC;AAAA,EACA;AAEA,CAAC;",
        "names": []
      }
    },
    {
      "name": "vite:json",
      "start": 1713208772463,
      "end": 1713208772463,
      "order": "normal"
    },
    {
      "name": "vite:worker",
      "start": 1713208772463,
      "end": 1713208772463,
      "order": "normal"
    },
    {
      "name": "vite:vue",
      "start": 1713208772463,
      "end": 1713208772464,
      "order": "normal"
    },
    {
      "name": "vite:vue-jsx",
      "start": 1713208772464,
      "end": 1713208772464,
      "order": "normal"
    },
    {
      "name": "replace",
      "start": 1713208772464,
      "end": 1713208772464,
      "order": "normal"
    },
    {
      "name": "nuxt:remove-plugin-metadata",
      "start": 1713208772464,
      "end": 1713208772464,
      "order": "normal"
    },
    {
      "name": "nuxt:chunk-error",
      "start": 1713208772464,
      "end": 1713208772464,
      "order": "normal"
    },
    {
      "name": "nuxt:components:imports",
      "start": 1713208772464,
      "end": 1713208772464,
      "order": "normal"
    },
    {
      "name": "replace",
      "start": 1713208772464,
      "end": 1713208772465,
      "order": "normal"
    },
    {
      "name": "ssr-styles",
      "start": 1713208772465,
      "end": 1713208772465,
      "order": "normal"
    },
    {
      "name": "vite:define",
      "start": 1713208772465,
      "end": 1713208772465,
      "order": "normal"
    },
    {
      "name": "vite:css-post",
      "start": 1713208772465,
      "end": 1713208772465,
      "order": "normal"
    },
    {
      "name": "vite:build-html",
      "start": 1713208772465,
      "end": 1713208772465,
      "order": "normal"
    },
    {
      "name": "vite:worker-import-meta-url",
      "start": 1713208772465,
      "end": 1713208772465,
      "order": "normal"
    },
    {
      "name": "vite:asset-import-meta-url",
      "start": 1713208772465,
      "end": 1713208772465,
      "order": "normal"
    },
    {
      "name": "commonjs",
      "start": 1713208772465,
      "end": 1713208772465,
      "order": "normal"
    },
    {
      "name": "vite:dynamic-import-vars",
      "start": 1713208772465,
      "end": 1713208772465,
      "order": "normal"
    },
    {
      "name": "vite:import-glob",
      "start": 1713208772465,
      "end": 1713208772465,
      "order": "normal"
    },
    {
      "name": "nuxt:composable-keys",
      "start": 1713208772465,
      "end": 1713208772466,
      "order": "post"
    },
    {
      "name": "unhead:use-seo-meta-transform",
      "start": 1713208772466,
      "end": 1713208772466,
      "order": "post"
    },
    {
      "name": "nuxtjs:i18n-resource",
      "start": 1713208772466,
      "end": 1713208772466,
      "order": "post"
    },
    {
      "name": "nuxtjs:i18n-meta-deprecation",
      "start": 1713208772466,
      "end": 1713208772466,
      "order": "post"
    },
    {
      "name": "nuxt:imports-transform",
      "start": 1713208772466,
      "end": 1713208772472,
      "order": "post"
    },
    {
      "name": "unctx:transform",
      "start": 1713208772472,
      "end": 1713208772472,
      "order": "post"
    },
    {
      "name": "nuxt:pages-macros-transform",
      "start": 1713208772472,
      "end": 1713208772472,
      "order": "post"
    },
    {
      "name": "nuxt:runtime-paths-dep",
      "start": 1713208772472,
      "end": 1713208772472,
      "order": "post"
    },
    {
      "name": "nuxt:route-injection-plugin",
      "start": 1713208772473,
      "end": 1713208772473,
      "order": "post"
    },
    {
      "name": "nuxt:components-loader",
      "start": 1713208772473,
      "end": 1713208772473,
      "order": "post"
    },
    {
      "name": "nuxt:tree-shake-composables:transform",
      "start": 1713208772473,
      "end": 1713208772473,
      "order": "post"
    },
    {
      "name": "vite:build-import-analysis",
      "start": 1713208772474,
      "end": 1713208772474,
      "order": "normal"
    },
    {
      "name": "vite:reporter",
      "start": 1713208772474,
      "end": 1713208772474,
      "order": "normal"
    }
  ]
}
