{
  "resolvedId": "/home/yalnguembu/Perso/quonte/components/TheFooter.vue?vue&type=script&setup=true&lang.ts",
  "transforms": [
    {
      "name": "vite:vue",
      "result": "import { defineComponent as _defineComponent } from 'vue'\nimport { createElementVNode as _createElementVNode, resolveComponent as _resolveComponent, withCtx as _withCtx, createVNode as _createVNode, unref as _unref, toDisplayString as _toDisplayString, createTextVNode as _createTextVNode, renderList as _renderList, Fragment as _Fragment, openBlock as _openBlock, createElementBlock as _createElementBlock, createBlock as _createBlock, resolveDynamicComponent as _resolveDynamicComponent } from \"vue\"\nimport _imports_0 from '@/assets/images/logo.svg'\n\n\nconst _hoisted_1 = { class: \"block min-h-4 w-full bg-gray-100 dark:bg-gray-800 dark:text-gray-100\" }\nconst _hoisted_2 = { class: \"grid grid-cols-1 gap-4 lg:grid-cols-4 lg:p-12\" }\nconst _hoisted_3 = { class: \"max-w-screen-xl items-center flex flex-col justify-between p-4 lg:items-start\" }\nconst _hoisted_4 = /*#__PURE__*/_createElementVNode(\"img\", {\n  src: _imports_0,\n  alt: \"\",\n  class: \"w-16 rotate-45\"\n}, null, -1)\nconst _hoisted_5 = /*#__PURE__*/_createElementVNode(\"span\", { class: \"bg-clip-text text-4xl bg-gradient-to-r from-green-500 dark:from-green-300 to-yellow-500 dark:to-yellow-500\" }, \"Quonte\", -1)\nconst _hoisted_6 = { class: \"px-4 py-4 text-gray-500 text-xl lg:text-base\" }\nconst _hoisted_7 = /*#__PURE__*/_createElementVNode(\"br\", null, null, -1)\nconst _hoisted_8 = { class: \"p-4 text-center lg:text-left\" }\nconst _hoisted_9 = /*#__PURE__*/_createElementVNode(\"h5\", { class: \"dark:text-gray-100 text-3xl lg:text-xl px-2 mb-2\" }, \" Products \", -1)\nconst _hoisted_10 = { class: \"p-4 text-center lg:text-left\" }\nconst _hoisted_11 = /*#__PURE__*/_createElementVNode(\"h5\", { class: \"dark:text-gray-100 text-3xl lg:text-xl px-2 mb-2\" }, \" About us \", -1)\nconst _hoisted_12 = { class: \"p-4 flex flex-col items-center justify-between lg:items-start\" }\nconst _hoisted_13 = /*#__PURE__*/_createElementVNode(\"h5\", { class: \"dark:text-gray-100 text-3xl lg:text-xl px-2 mb-2\" }, \" Get in touch \", -1)\nconst _hoisted_14 = /*#__PURE__*/_createElementVNode(\"p\", { class: \"px-2 py-4 text-gray-500 text-xl lg:text-base\" }, [\n  /*#__PURE__*/_createTextVNode(\" Question or feedback? \"),\n  /*#__PURE__*/_createElementVNode(\"br\"),\n  /*#__PURE__*/_createTextVNode(\" We'd love to hear from you \")\n], -1)\nconst _hoisted_15 = { class: \"flex\" }\n\nimport MenuItem from \"./menu/MenuItem.vue\";\nimport { footerItems } from \"@/utils/data\";\nimport AnimeOnScroll from \"@/components/AnimeOnScroll.vue\";\nimport LinkWrapper from \"./LinkWrapper.vue\";\n\n\nexport default /*#__PURE__*/_defineComponent({\n  __name: 'TheFooter',\n  setup(__props) {\n\nconst thisYear = new Date().getFullYear();\n\nreturn (_ctx: any,_cache: any) => {\n  const _component_RouterLink = _resolveComponent(\"RouterLink\")!\n\n  return (_openBlock(), _createElementBlock(\"footer\", _hoisted_1, [\n    _createElementVNode(\"div\", _hoisted_2, [\n      _createVNode(AnimeOnScroll, null, {\n        default: _withCtx(() => [\n          _createElementVNode(\"div\", _hoisted_3, [\n            _createVNode(_component_RouterLink, {\n              to: \"/\",\n              class: \"text-xl font-bold text-transparent flex flex-col items-center px-4\"\n            }, {\n              default: _withCtx(() => [\n                _hoisted_4,\n                _hoisted_5\n              ]),\n              _: 1\n            }),\n            _createElementVNode(\"p\", _hoisted_6, [\n              _createTextVNode(\" © \" + _toDisplayString(_unref(thisYear)) + \" Quonte inc\", 1),\n              _hoisted_7,\n              _createTextVNode(\" By \"),\n              _createVNode(LinkWrapper, {\n                path: \"https://yalnguembu.netlify.app/\",\n                title: \"visit Young-Tech website\",\n                \"is-external\": \"\",\n                class: \"hover:text-blue-400 hover:underline italic font-sans font-bold\"\n              }, {\n                default: _withCtx(() => [\n                  _createTextVNode(\" Young-Tech \")\n                ]),\n                _: 1\n              })\n            ])\n          ])\n        ]),\n        _: 1\n      }),\n      _createVNode(AnimeOnScroll, null, {\n        default: _withCtx(() => [\n          _createElementVNode(\"div\", _hoisted_8, [\n            _hoisted_9,\n            _createElementVNode(\"ul\", null, [\n              (_openBlock(true), _createElementBlock(_Fragment, null, _renderList(_unref(footerItems)[0], (item, index) => {\n                return (_openBlock(), _createBlock(MenuItem, {\n                  key: index,\n                  path: item.path,\n                  label: item.label,\n                  theme: {\n                label: 'text-xl lg:text-base',\n                item: 'block py-3 rounded px-2 text-gray-500 hover:text-green-800 hover:font-bold dark:hover:text-gray-100',\n              }\n                }, null, 8, [\"path\", \"label\"]))\n              }), 128))\n            ])\n          ])\n        ]),\n        _: 1\n      }),\n      _createVNode(AnimeOnScroll, null, {\n        default: _withCtx(() => [\n          _createElementVNode(\"div\", _hoisted_10, [\n            _hoisted_11,\n            _createElementVNode(\"ul\", null, [\n              (_openBlock(true), _createElementBlock(_Fragment, null, _renderList(_unref(footerItems)[1], (item, index) => {\n                return (_openBlock(), _createBlock(MenuItem, {\n                  key: index,\n                  path: item.path,\n                  label: item.label,\n                  theme: {\n                label: 'text-xl lg:text-base',\n                item: 'block py-3 rounded px-2 text-gray-500 hover:text-green-800 hover:font-bold  dark:hover:text-gray-100',\n              }\n                }, null, 8, [\"path\", \"label\"]))\n              }), 128))\n            ])\n          ])\n        ]),\n        _: 1\n      }),\n      _createVNode(AnimeOnScroll, null, {\n        default: _withCtx(() => [\n          _createElementVNode(\"div\", _hoisted_12, [\n            _hoisted_13,\n            _hoisted_14,\n            _createElementVNode(\"ul\", _hoisted_15, [\n              (_openBlock(true), _createElementBlock(_Fragment, null, _renderList(_unref(footerItems)[2], (item, index) => {\n                return (_openBlock(), _createBlock(LinkWrapper, {\n                  key: index,\n                  path: item.path,\n                  isExternal: \"\",\n                  class: \"block p-2 px-3 mr-2 rounded-md hover:bg-gray-300 dark:hover:bg-gray-700\"\n                }, {\n                  default: _withCtx(() => [\n                    (_openBlock(), _createBlock(_resolveDynamicComponent(item.icon), { class: \"w-5 h-5 dark:fill-gray-100\" }))\n                  ]),\n                  _: 2\n                }, 1032, [\"path\"]))\n              }), 128))\n            ])\n          ])\n        ]),\n        _: 1\n      })\n    ])\n  ]))\n}\n}\n\n})",
      "start": 1713208772216,
      "end": 1713208772216
    },
    {
      "name": "nuxt:layer-aliasing",
      "start": 1713208772217,
      "end": 1713208772217,
      "order": "pre"
    },
    {
      "name": "nuxt:server-devonly:transform",
      "start": 1713208772217,
      "end": 1713208772217,
      "order": "pre"
    },
    {
      "name": "unplugin-vue-i18n",
      "start": 1713208772217,
      "end": 1713208772217,
      "order": "pre"
    },
    {
      "name": "nuxtjs:i18n-macros-transform",
      "start": 1713208772217,
      "end": 1713208772218,
      "order": "pre"
    },
    {
      "name": "nuxt:client-fallback-auto-id",
      "start": 1713208772218,
      "end": 1713208772218,
      "order": "pre"
    },
    {
      "name": "vite:css",
      "start": 1713208772218,
      "end": 1713208772218,
      "order": "normal"
    },
    {
      "name": "vite:esbuild",
      "result": "import { defineComponent as _defineComponent } from \"vue\";\nimport { createElementVNode as _createElementVNode, resolveComponent as _resolveComponent, withCtx as _withCtx, createVNode as _createVNode, unref as _unref, toDisplayString as _toDisplayString, createTextVNode as _createTextVNode, renderList as _renderList, Fragment as _Fragment, openBlock as _openBlock, createElementBlock as _createElementBlock, createBlock as _createBlock, resolveDynamicComponent as _resolveDynamicComponent } from \"vue\";\nimport _imports_0 from \"@/assets/images/logo.svg\";\nconst _hoisted_1 = { class: \"block min-h-4 w-full bg-gray-100 dark:bg-gray-800 dark:text-gray-100\" };\nconst _hoisted_2 = { class: \"grid grid-cols-1 gap-4 lg:grid-cols-4 lg:p-12\" };\nconst _hoisted_3 = { class: \"max-w-screen-xl items-center flex flex-col justify-between p-4 lg:items-start\" };\nconst _hoisted_4 = /* @__PURE__ */ _createElementVNode(\"img\", {\n  src: _imports_0,\n  alt: \"\",\n  class: \"w-16 rotate-45\"\n}, null, -1);\nconst _hoisted_5 = /* @__PURE__ */ _createElementVNode(\"span\", { class: \"bg-clip-text text-4xl bg-gradient-to-r from-green-500 dark:from-green-300 to-yellow-500 dark:to-yellow-500\" }, \"Quonte\", -1);\nconst _hoisted_6 = { class: \"px-4 py-4 text-gray-500 text-xl lg:text-base\" };\nconst _hoisted_7 = /* @__PURE__ */ _createElementVNode(\"br\", null, null, -1);\nconst _hoisted_8 = { class: \"p-4 text-center lg:text-left\" };\nconst _hoisted_9 = /* @__PURE__ */ _createElementVNode(\"h5\", { class: \"dark:text-gray-100 text-3xl lg:text-xl px-2 mb-2\" }, \" Products \", -1);\nconst _hoisted_10 = { class: \"p-4 text-center lg:text-left\" };\nconst _hoisted_11 = /* @__PURE__ */ _createElementVNode(\"h5\", { class: \"dark:text-gray-100 text-3xl lg:text-xl px-2 mb-2\" }, \" About us \", -1);\nconst _hoisted_12 = { class: \"p-4 flex flex-col items-center justify-between lg:items-start\" };\nconst _hoisted_13 = /* @__PURE__ */ _createElementVNode(\"h5\", { class: \"dark:text-gray-100 text-3xl lg:text-xl px-2 mb-2\" }, \" Get in touch \", -1);\nconst _hoisted_14 = /* @__PURE__ */ _createElementVNode(\"p\", { class: \"px-2 py-4 text-gray-500 text-xl lg:text-base\" }, [\n  /* @__PURE__ */ _createTextVNode(\" Question or feedback? \"),\n  /* @__PURE__ */ _createElementVNode(\"br\"),\n  /* @__PURE__ */ _createTextVNode(\" We'd love to hear from you \")\n], -1);\nconst _hoisted_15 = { class: \"flex\" };\nimport MenuItem from \"./menu/MenuItem.vue\";\nimport { footerItems } from \"@/utils/data\";\nimport AnimeOnScroll from \"@/components/AnimeOnScroll.vue\";\nimport LinkWrapper from \"./LinkWrapper.vue\";\nexport default /* @__PURE__ */ _defineComponent({\n  __name: \"TheFooter\",\n  setup(__props) {\n    const thisYear = (/* @__PURE__ */ new Date()).getFullYear();\n    return (_ctx, _cache) => {\n      const _component_RouterLink = _resolveComponent(\"RouterLink\");\n      return _openBlock(), _createElementBlock(\"footer\", _hoisted_1, [\n        _createElementVNode(\"div\", _hoisted_2, [\n          _createVNode(AnimeOnScroll, null, {\n            default: _withCtx(() => [\n              _createElementVNode(\"div\", _hoisted_3, [\n                _createVNode(_component_RouterLink, {\n                  to: \"/\",\n                  class: \"text-xl font-bold text-transparent flex flex-col items-center px-4\"\n                }, {\n                  default: _withCtx(() => [\n                    _hoisted_4,\n                    _hoisted_5\n                  ]),\n                  _: 1\n                }),\n                _createElementVNode(\"p\", _hoisted_6, [\n                  _createTextVNode(\" © \" + _toDisplayString(_unref(thisYear)) + \" Quonte inc\", 1),\n                  _hoisted_7,\n                  _createTextVNode(\" By \"),\n                  _createVNode(LinkWrapper, {\n                    path: \"https://yalnguembu.netlify.app/\",\n                    title: \"visit Young-Tech website\",\n                    \"is-external\": \"\",\n                    class: \"hover:text-blue-400 hover:underline italic font-sans font-bold\"\n                  }, {\n                    default: _withCtx(() => [\n                      _createTextVNode(\" Young-Tech \")\n                    ]),\n                    _: 1\n                  })\n                ])\n              ])\n            ]),\n            _: 1\n          }),\n          _createVNode(AnimeOnScroll, null, {\n            default: _withCtx(() => [\n              _createElementVNode(\"div\", _hoisted_8, [\n                _hoisted_9,\n                _createElementVNode(\"ul\", null, [\n                  (_openBlock(true), _createElementBlock(_Fragment, null, _renderList(_unref(footerItems)[0], (item, index) => {\n                    return _openBlock(), _createBlock(MenuItem, {\n                      key: index,\n                      path: item.path,\n                      label: item.label,\n                      theme: {\n                        label: \"text-xl lg:text-base\",\n                        item: \"block py-3 rounded px-2 text-gray-500 hover:text-green-800 hover:font-bold dark:hover:text-gray-100\"\n                      }\n                    }, null, 8, [\"path\", \"label\"]);\n                  }), 128))\n                ])\n              ])\n            ]),\n            _: 1\n          }),\n          _createVNode(AnimeOnScroll, null, {\n            default: _withCtx(() => [\n              _createElementVNode(\"div\", _hoisted_10, [\n                _hoisted_11,\n                _createElementVNode(\"ul\", null, [\n                  (_openBlock(true), _createElementBlock(_Fragment, null, _renderList(_unref(footerItems)[1], (item, index) => {\n                    return _openBlock(), _createBlock(MenuItem, {\n                      key: index,\n                      path: item.path,\n                      label: item.label,\n                      theme: {\n                        label: \"text-xl lg:text-base\",\n                        item: \"block py-3 rounded px-2 text-gray-500 hover:text-green-800 hover:font-bold  dark:hover:text-gray-100\"\n                      }\n                    }, null, 8, [\"path\", \"label\"]);\n                  }), 128))\n                ])\n              ])\n            ]),\n            _: 1\n          }),\n          _createVNode(AnimeOnScroll, null, {\n            default: _withCtx(() => [\n              _createElementVNode(\"div\", _hoisted_12, [\n                _hoisted_13,\n                _hoisted_14,\n                _createElementVNode(\"ul\", _hoisted_15, [\n                  (_openBlock(true), _createElementBlock(_Fragment, null, _renderList(_unref(footerItems)[2], (item, index) => {\n                    return _openBlock(), _createBlock(LinkWrapper, {\n                      key: index,\n                      path: item.path,\n                      isExternal: \"\",\n                      class: \"block p-2 px-3 mr-2 rounded-md hover:bg-gray-300 dark:hover:bg-gray-700\"\n                    }, {\n                      default: _withCtx(() => [\n                        (_openBlock(), _createBlock(_resolveDynamicComponent(item.icon), { class: \"w-5 h-5 dark:fill-gray-100\" }))\n                      ]),\n                      _: 2\n                    }, 1032, [\"path\"]);\n                  }), 128))\n                ])\n              ])\n            ]),\n            _: 1\n          })\n        ])\n      ]);\n    };\n  }\n});\n",
      "start": 1713208772219,
      "end": 1713208772262,
      "order": "normal",
      "sourcemaps": {
        "version": 3,
        "sources": [
          "/home/yalnguembu/Perso/quonte/components/TheFooter.vue?vue&type=script&setup=true&lang.ts"
        ],
        "sourcesContent": [
          "import { defineComponent as _defineComponent } from 'vue'\nimport { createElementVNode as _createElementVNode, resolveComponent as _resolveComponent, withCtx as _withCtx, createVNode as _createVNode, unref as _unref, toDisplayString as _toDisplayString, createTextVNode as _createTextVNode, renderList as _renderList, Fragment as _Fragment, openBlock as _openBlock, createElementBlock as _createElementBlock, createBlock as _createBlock, resolveDynamicComponent as _resolveDynamicComponent } from \"vue\"\nimport _imports_0 from '@/assets/images/logo.svg'\n\n\nconst _hoisted_1 = { class: \"block min-h-4 w-full bg-gray-100 dark:bg-gray-800 dark:text-gray-100\" }\nconst _hoisted_2 = { class: \"grid grid-cols-1 gap-4 lg:grid-cols-4 lg:p-12\" }\nconst _hoisted_3 = { class: \"max-w-screen-xl items-center flex flex-col justify-between p-4 lg:items-start\" }\nconst _hoisted_4 = /*#__PURE__*/_createElementVNode(\"img\", {\n  src: _imports_0,\n  alt: \"\",\n  class: \"w-16 rotate-45\"\n}, null, -1)\nconst _hoisted_5 = /*#__PURE__*/_createElementVNode(\"span\", { class: \"bg-clip-text text-4xl bg-gradient-to-r from-green-500 dark:from-green-300 to-yellow-500 dark:to-yellow-500\" }, \"Quonte\", -1)\nconst _hoisted_6 = { class: \"px-4 py-4 text-gray-500 text-xl lg:text-base\" }\nconst _hoisted_7 = /*#__PURE__*/_createElementVNode(\"br\", null, null, -1)\nconst _hoisted_8 = { class: \"p-4 text-center lg:text-left\" }\nconst _hoisted_9 = /*#__PURE__*/_createElementVNode(\"h5\", { class: \"dark:text-gray-100 text-3xl lg:text-xl px-2 mb-2\" }, \" Products \", -1)\nconst _hoisted_10 = { class: \"p-4 text-center lg:text-left\" }\nconst _hoisted_11 = /*#__PURE__*/_createElementVNode(\"h5\", { class: \"dark:text-gray-100 text-3xl lg:text-xl px-2 mb-2\" }, \" About us \", -1)\nconst _hoisted_12 = { class: \"p-4 flex flex-col items-center justify-between lg:items-start\" }\nconst _hoisted_13 = /*#__PURE__*/_createElementVNode(\"h5\", { class: \"dark:text-gray-100 text-3xl lg:text-xl px-2 mb-2\" }, \" Get in touch \", -1)\nconst _hoisted_14 = /*#__PURE__*/_createElementVNode(\"p\", { class: \"px-2 py-4 text-gray-500 text-xl lg:text-base\" }, [\n  /*#__PURE__*/_createTextVNode(\" Question or feedback? \"),\n  /*#__PURE__*/_createElementVNode(\"br\"),\n  /*#__PURE__*/_createTextVNode(\" We'd love to hear from you \")\n], -1)\nconst _hoisted_15 = { class: \"flex\" }\n\nimport MenuItem from \"./menu/MenuItem.vue\";\nimport { footerItems } from \"@/utils/data\";\nimport AnimeOnScroll from \"@/components/AnimeOnScroll.vue\";\nimport LinkWrapper from \"./LinkWrapper.vue\";\n\n\nexport default /*#__PURE__*/_defineComponent({\n  __name: 'TheFooter',\n  setup(__props) {\n\nconst thisYear = new Date().getFullYear();\n\nreturn (_ctx: any,_cache: any) => {\n  const _component_RouterLink = _resolveComponent(\"RouterLink\")!\n\n  return (_openBlock(), _createElementBlock(\"footer\", _hoisted_1, [\n    _createElementVNode(\"div\", _hoisted_2, [\n      _createVNode(AnimeOnScroll, null, {\n        default: _withCtx(() => [\n          _createElementVNode(\"div\", _hoisted_3, [\n            _createVNode(_component_RouterLink, {\n              to: \"/\",\n              class: \"text-xl font-bold text-transparent flex flex-col items-center px-4\"\n            }, {\n              default: _withCtx(() => [\n                _hoisted_4,\n                _hoisted_5\n              ]),\n              _: 1\n            }),\n            _createElementVNode(\"p\", _hoisted_6, [\n              _createTextVNode(\" © \" + _toDisplayString(_unref(thisYear)) + \" Quonte inc\", 1),\n              _hoisted_7,\n              _createTextVNode(\" By \"),\n              _createVNode(LinkWrapper, {\n                path: \"https://yalnguembu.netlify.app/\",\n                title: \"visit Young-Tech website\",\n                \"is-external\": \"\",\n                class: \"hover:text-blue-400 hover:underline italic font-sans font-bold\"\n              }, {\n                default: _withCtx(() => [\n                  _createTextVNode(\" Young-Tech \")\n                ]),\n                _: 1\n              })\n            ])\n          ])\n        ]),\n        _: 1\n      }),\n      _createVNode(AnimeOnScroll, null, {\n        default: _withCtx(() => [\n          _createElementVNode(\"div\", _hoisted_8, [\n            _hoisted_9,\n            _createElementVNode(\"ul\", null, [\n              (_openBlock(true), _createElementBlock(_Fragment, null, _renderList(_unref(footerItems)[0], (item, index) => {\n                return (_openBlock(), _createBlock(MenuItem, {\n                  key: index,\n                  path: item.path,\n                  label: item.label,\n                  theme: {\n                label: 'text-xl lg:text-base',\n                item: 'block py-3 rounded px-2 text-gray-500 hover:text-green-800 hover:font-bold dark:hover:text-gray-100',\n              }\n                }, null, 8, [\"path\", \"label\"]))\n              }), 128))\n            ])\n          ])\n        ]),\n        _: 1\n      }),\n      _createVNode(AnimeOnScroll, null, {\n        default: _withCtx(() => [\n          _createElementVNode(\"div\", _hoisted_10, [\n            _hoisted_11,\n            _createElementVNode(\"ul\", null, [\n              (_openBlock(true), _createElementBlock(_Fragment, null, _renderList(_unref(footerItems)[1], (item, index) => {\n                return (_openBlock(), _createBlock(MenuItem, {\n                  key: index,\n                  path: item.path,\n                  label: item.label,\n                  theme: {\n                label: 'text-xl lg:text-base',\n                item: 'block py-3 rounded px-2 text-gray-500 hover:text-green-800 hover:font-bold  dark:hover:text-gray-100',\n              }\n                }, null, 8, [\"path\", \"label\"]))\n              }), 128))\n            ])\n          ])\n        ]),\n        _: 1\n      }),\n      _createVNode(AnimeOnScroll, null, {\n        default: _withCtx(() => [\n          _createElementVNode(\"div\", _hoisted_12, [\n            _hoisted_13,\n            _hoisted_14,\n            _createElementVNode(\"ul\", _hoisted_15, [\n              (_openBlock(true), _createElementBlock(_Fragment, null, _renderList(_unref(footerItems)[2], (item, index) => {\n                return (_openBlock(), _createBlock(LinkWrapper, {\n                  key: index,\n                  path: item.path,\n                  isExternal: \"\",\n                  class: \"block p-2 px-3 mr-2 rounded-md hover:bg-gray-300 dark:hover:bg-gray-700\"\n                }, {\n                  default: _withCtx(() => [\n                    (_openBlock(), _createBlock(_resolveDynamicComponent(item.icon), { class: \"w-5 h-5 dark:fill-gray-100\" }))\n                  ]),\n                  _: 2\n                }, 1032, [\"path\"]))\n              }), 128))\n            ])\n          ])\n        ]),\n        _: 1\n      })\n    ])\n  ]))\n}\n}\n\n})"
        ],
        "mappings": "AAAA,SAAS,mBAAmB,wBAAwB;AACpD,SAAS,sBAAsB,qBAAqB,oBAAoB,mBAAmB,WAAW,UAAU,eAAe,cAAc,SAAS,QAAQ,mBAAmB,kBAAkB,mBAAmB,kBAAkB,cAAc,aAAa,YAAY,WAAW,aAAa,YAAY,sBAAsB,qBAAqB,eAAe,cAAc,2BAA2B,gCAAgC;AACtb,OAAO,gBAAgB;AAGvB,MAAM,aAAa,EAAE,OAAO,uEAAuE;AACnG,MAAM,aAAa,EAAE,OAAO,gDAAgD;AAC5E,MAAM,aAAa,EAAE,OAAO,gFAAgF;AAC5G,MAAM,aAA0B,oCAAoB,OAAO;AAAA,EACzD,KAAK;AAAA,EACL,KAAK;AAAA,EACL,OAAO;AACT,GAAG,MAAM,EAAE;AACX,MAAM,aAA0B,oCAAoB,QAAQ,EAAE,OAAO,6GAA6G,GAAG,UAAU,EAAE;AACjM,MAAM,aAAa,EAAE,OAAO,+CAA+C;AAC3E,MAAM,aAA0B,oCAAoB,MAAM,MAAM,MAAM,EAAE;AACxE,MAAM,aAAa,EAAE,OAAO,+BAA+B;AAC3D,MAAM,aAA0B,oCAAoB,MAAM,EAAE,OAAO,mDAAmD,GAAG,cAAc,EAAE;AACzI,MAAM,cAAc,EAAE,OAAO,+BAA+B;AAC5D,MAAM,cAA2B,oCAAoB,MAAM,EAAE,OAAO,mDAAmD,GAAG,cAAc,EAAE;AAC1I,MAAM,cAAc,EAAE,OAAO,gEAAgE;AAC7F,MAAM,cAA2B,oCAAoB,MAAM,EAAE,OAAO,mDAAmD,GAAG,kBAAkB,EAAE;AAC9I,MAAM,cAA2B,oCAAoB,KAAK,EAAE,OAAO,+CAA+C,GAAG;AAAA,EACtG,iCAAiB,yBAAyB;AAAA,EAC1C,oCAAoB,IAAI;AAAA,EACxB,iCAAiB,8BAA8B;AAC9D,GAAG,EAAE;AACL,MAAM,cAAc,EAAE,OAAO,OAAO;AAEpC,OAAO,cAAc;AACrB,SAAS,mBAAmB;AAC5B,OAAO,mBAAmB;AAC1B,OAAO,iBAAiB;AAGxB,eAA4B,iCAAiB;AAAA,EAC3C,QAAQ;AAAA,EACR,MAAM,SAAS;AAEjB,UAAM,YAAW,oBAAI,KAAK,GAAE,YAAY;AAExC,WAAO,CAAC,MAAU,WAAgB;AAChC,YAAM,wBAAwB,kBAAkB,YAAY;AAE5D,aAAQ,WAAW,GAAG,oBAAoB,UAAU,YAAY;AAAA,QAC9D,oBAAoB,OAAO,YAAY;AAAA,UACrC,aAAa,eAAe,MAAM;AAAA,YAChC,SAAS,SAAS,MAAM;AAAA,cACtB,oBAAoB,OAAO,YAAY;AAAA,gBACrC,aAAa,uBAAuB;AAAA,kBAClC,IAAI;AAAA,kBACJ,OAAO;AAAA,gBACT,GAAG;AAAA,kBACD,SAAS,SAAS,MAAM;AAAA,oBACtB;AAAA,oBACA;AAAA,kBACF,CAAC;AAAA,kBACD,GAAG;AAAA,gBACL,CAAC;AAAA,gBACD,oBAAoB,KAAK,YAAY;AAAA,kBACnC,iBAAiB,QAAQ,iBAAiB,OAAO,QAAQ,CAAC,IAAI,eAAe,CAAC;AAAA,kBAC9E;AAAA,kBACA,iBAAiB,MAAM;AAAA,kBACvB,aAAa,aAAa;AAAA,oBACxB,MAAM;AAAA,oBACN,OAAO;AAAA,oBACP,eAAe;AAAA,oBACf,OAAO;AAAA,kBACT,GAAG;AAAA,oBACD,SAAS,SAAS,MAAM;AAAA,sBACtB,iBAAiB,cAAc;AAAA,oBACjC,CAAC;AAAA,oBACD,GAAG;AAAA,kBACL,CAAC;AAAA,gBACH,CAAC;AAAA,cACH,CAAC;AAAA,YACH,CAAC;AAAA,YACD,GAAG;AAAA,UACL,CAAC;AAAA,UACD,aAAa,eAAe,MAAM;AAAA,YAChC,SAAS,SAAS,MAAM;AAAA,cACtB,oBAAoB,OAAO,YAAY;AAAA,gBACrC;AAAA,gBACA,oBAAoB,MAAM,MAAM;AAAA,mBAC7B,WAAW,IAAI,GAAG,oBAAoB,WAAW,MAAM,YAAY,OAAO,WAAW,EAAE,CAAC,GAAG,CAAC,MAAM,UAAU;AAC3G,2BAAQ,WAAW,GAAG,aAAa,UAAU;AAAA,sBAC3C,KAAK;AAAA,sBACL,MAAM,KAAK;AAAA,sBACX,OAAO,KAAK;AAAA,sBACZ,OAAO;AAAA,wBACT,OAAO;AAAA,wBACP,MAAM;AAAA,sBACR;AAAA,oBACE,GAAG,MAAM,GAAG,CAAC,QAAQ,OAAO,CAAC;AAAA,kBAC/B,CAAC,GAAG,GAAG;AAAA,gBACT,CAAC;AAAA,cACH,CAAC;AAAA,YACH,CAAC;AAAA,YACD,GAAG;AAAA,UACL,CAAC;AAAA,UACD,aAAa,eAAe,MAAM;AAAA,YAChC,SAAS,SAAS,MAAM;AAAA,cACtB,oBAAoB,OAAO,aAAa;AAAA,gBACtC;AAAA,gBACA,oBAAoB,MAAM,MAAM;AAAA,mBAC7B,WAAW,IAAI,GAAG,oBAAoB,WAAW,MAAM,YAAY,OAAO,WAAW,EAAE,CAAC,GAAG,CAAC,MAAM,UAAU;AAC3G,2BAAQ,WAAW,GAAG,aAAa,UAAU;AAAA,sBAC3C,KAAK;AAAA,sBACL,MAAM,KAAK;AAAA,sBACX,OAAO,KAAK;AAAA,sBACZ,OAAO;AAAA,wBACT,OAAO;AAAA,wBACP,MAAM;AAAA,sBACR;AAAA,oBACE,GAAG,MAAM,GAAG,CAAC,QAAQ,OAAO,CAAC;AAAA,kBAC/B,CAAC,GAAG,GAAG;AAAA,gBACT,CAAC;AAAA,cACH,CAAC;AAAA,YACH,CAAC;AAAA,YACD,GAAG;AAAA,UACL,CAAC;AAAA,UACD,aAAa,eAAe,MAAM;AAAA,YAChC,SAAS,SAAS,MAAM;AAAA,cACtB,oBAAoB,OAAO,aAAa;AAAA,gBACtC;AAAA,gBACA;AAAA,gBACA,oBAAoB,MAAM,aAAa;AAAA,mBACpC,WAAW,IAAI,GAAG,oBAAoB,WAAW,MAAM,YAAY,OAAO,WAAW,EAAE,CAAC,GAAG,CAAC,MAAM,UAAU;AAC3G,2BAAQ,WAAW,GAAG,aAAa,aAAa;AAAA,sBAC9C,KAAK;AAAA,sBACL,MAAM,KAAK;AAAA,sBACX,YAAY;AAAA,sBACZ,OAAO;AAAA,oBACT,GAAG;AAAA,sBACD,SAAS,SAAS,MAAM;AAAA,yBACrB,WAAW,GAAG,aAAa,yBAAyB,KAAK,IAAI,GAAG,EAAE,OAAO,6BAA6B,CAAC;AAAA,sBAC1G,CAAC;AAAA,sBACD,GAAG;AAAA,oBACL,GAAG,MAAM,CAAC,MAAM,CAAC;AAAA,kBACnB,CAAC,GAAG,GAAG;AAAA,gBACT,CAAC;AAAA,cACH,CAAC;AAAA,YACH,CAAC;AAAA,YACD,GAAG;AAAA,UACL,CAAC;AAAA,QACH,CAAC;AAAA,MACH,CAAC;AAAA,IACH;AAAA,EACA;AAEA,CAAC;",
        "names": []
      }
    },
    {
      "name": "vite:json",
      "start": 1713208772262,
      "end": 1713208772262,
      "order": "normal"
    },
    {
      "name": "vite:worker",
      "start": 1713208772262,
      "end": 1713208772262,
      "order": "normal"
    },
    {
      "name": "vite:vue",
      "start": 1713208772262,
      "end": 1713208772262,
      "order": "normal"
    },
    {
      "name": "vite:vue-jsx",
      "start": 1713208772262,
      "end": 1713208772262,
      "order": "normal"
    },
    {
      "name": "replace",
      "start": 1713208772263,
      "end": 1713208772263,
      "order": "normal"
    },
    {
      "name": "nuxt:remove-plugin-metadata",
      "start": 1713208772263,
      "end": 1713208772263,
      "order": "normal"
    },
    {
      "name": "nuxt:chunk-error",
      "start": 1713208772263,
      "end": 1713208772263,
      "order": "normal"
    },
    {
      "name": "nuxt:components:imports",
      "start": 1713208772263,
      "end": 1713208772263,
      "order": "normal"
    },
    {
      "name": "replace",
      "start": 1713208772263,
      "end": 1713208772263,
      "order": "normal"
    },
    {
      "name": "ssr-styles",
      "start": 1713208772263,
      "end": 1713208772263,
      "order": "normal"
    },
    {
      "name": "vite:define",
      "start": 1713208772263,
      "end": 1713208772263,
      "order": "normal"
    },
    {
      "name": "vite:css-post",
      "start": 1713208772263,
      "end": 1713208772263,
      "order": "normal"
    },
    {
      "name": "vite:build-html",
      "start": 1713208772263,
      "end": 1713208772263,
      "order": "normal"
    },
    {
      "name": "vite:worker-import-meta-url",
      "start": 1713208772263,
      "end": 1713208772263,
      "order": "normal"
    },
    {
      "name": "vite:asset-import-meta-url",
      "start": 1713208772263,
      "end": 1713208772263,
      "order": "normal"
    },
    {
      "name": "commonjs",
      "start": 1713208772263,
      "end": 1713208772263,
      "order": "normal"
    },
    {
      "name": "vite:dynamic-import-vars",
      "start": 1713208772263,
      "end": 1713208772263,
      "order": "normal"
    },
    {
      "name": "vite:import-glob",
      "start": 1713208772263,
      "end": 1713208772263,
      "order": "normal"
    },
    {
      "name": "nuxt:composable-keys",
      "start": 1713208772264,
      "end": 1713208772264,
      "order": "post"
    },
    {
      "name": "unhead:use-seo-meta-transform",
      "start": 1713208772264,
      "end": 1713208772264,
      "order": "post"
    },
    {
      "name": "nuxtjs:i18n-resource",
      "start": 1713208772264,
      "end": 1713208772264,
      "order": "post"
    },
    {
      "name": "nuxtjs:i18n-meta-deprecation",
      "start": 1713208772264,
      "end": 1713208772264,
      "order": "post"
    },
    {
      "name": "nuxt:imports-transform",
      "start": 1713208772264,
      "end": 1713208772271,
      "order": "post"
    },
    {
      "name": "unctx:transform",
      "start": 1713208772273,
      "end": 1713208772273,
      "order": "post"
    },
    {
      "name": "nuxt:pages-macros-transform",
      "start": 1713208772273,
      "end": 1713208772273,
      "order": "post"
    },
    {
      "name": "nuxt:runtime-paths-dep",
      "start": 1713208772273,
      "end": 1713208772273,
      "order": "post"
    },
    {
      "name": "nuxt:route-injection-plugin",
      "start": 1713208772273,
      "end": 1713208772274,
      "order": "post"
    },
    {
      "name": "nuxt:components-loader",
      "start": 1713208772274,
      "end": 1713208772274,
      "order": "post"
    },
    {
      "name": "nuxt:tree-shake-composables:transform",
      "start": 1713208772274,
      "end": 1713208772274,
      "order": "post"
    },
    {
      "name": "vite:build-import-analysis",
      "start": 1713208772275,
      "end": 1713208772275,
      "order": "normal"
    },
    {
      "name": "vite:reporter",
      "start": 1713208772275,
      "end": 1713208772275,
      "order": "normal"
    }
  ]
}
